uw/__init__.py
uw-0.0.5.dist-info/licenses/LICENSE
uw-0.0.5.dist-info/METADATA
uw-0.0.5.dist-info/WHEEL
uw-0.0.5.dist-info/top_level.txt
uw-0.0.5.dist-info/RECORD
