Metadata-Version: 2.4
Name: uw
Version: 0.0.5
Summary: useful decorators
Home-page: https://github.com/t-c-w/uw
Author: Thor Whalen
License: apache-2.0
Platform: any
License-File: LICENSE
Dynamic: license-file
